{
  "id": "channel.call-of-duty-free",
  "sectionId": "call-of-duty-free",
  "videos": [
    {
      "id": "video.call-of-duty-free.001",
      "playlistIndex": 7,
      "title": "History of Roadside Lodging | The Henry Ford’s Innovation Nation",
      "channel": "The Henry Ford",
      "url": "https://www.youtube.com/watch?v=5PIwo-kQcuQ",
      "duration": "3:57",
      "uploadDate": "Unknown",
      "contentType": "historical explainer",
      "formatStyle": "mixed or unknown",
      "score": 6.8,
      "verdict": "Useful WSC support, especially with teacher framing.",
      "description": "Contextual video about History of Roadside Lodging | The Henry Ford’s Innovation Nation. WSC link: Call of Duty-Free / Tourism types.",
      "keyTerms": [
        "henry",
        "ford",
        "history",
        "roadside",
        "lodging",
        "innovation",
        "nation"
      ],
      "transcriptAvailable": false,
      "sectionIds": [
        "call-of-duty-free"
      ],
      "sectionTitles": [
        "Call of Duty-Free"
      ],
      "entryTitles": [
        "From Roadside Stops to Hotels"
      ],
      "bigIdeaLabels": [
        "Tourism",
        "Journeys",
        "Drafts & Prototypes",
        "Prediction",
        "Routes, Roads & Navigation",
        "Progress",
        "Tourism types",
        "Copying, borrowing, and innovation",
        "From inns to hotels",
        "Maintenance vs innovation"
      ],
      "bigIdeaIds": [
        "tourism",
        "journeys",
        "drafts-and-prototypes",
        "prediction",
        "routes-roads-and-navigation",
        "progress",
        "tourism-types",
        "copying-borrowing-and-innovation",
        "from-inns-to-hotels",
        "maintenance-vs-innovation"
      ],
      "subjectLabels": [
        "History"
      ],
      "subjectIds": [
        "history"
      ],
      "connections": [
        {
          "kind": "entry",
          "sectionId": "call-of-duty-free",
          "sectionTitle": "Call of Duty-Free",
          "entryTitle": "From Roadside Stops to Hotels",
          "why": "Approved review placement under From Roadside Stops to Hotels."
        }
      ],
      "sourceId": "playlist-007-5PIwo-kQcuQ",
      "canonicalSectionId": "call-of-duty-free",
      "assetId": null
    },
    {
      "id": "video.call-of-duty-free.002",
      "playlistIndex": 52,
      "title": "The Silk Road: Connecting the ancient world through trade - Shannon Harris Castelo",
      "channel": "TED-Ed",
      "url": "https://www.youtube.com/watch?v=vn3e37VWc0k",
      "duration": "5:20",
      "uploadDate": "2014-06-03T08:00:39-07:00",
      "viewCount": 4249466,
      "contentType": "pedagogical explainer",
      "formatStyle": "animation / voiceover",
      "score": 7.3,
      "verdict": "Useful WSC support, especially with teacher framing.",
      "description": "View full lesson: http://ed.ted.com/lessons/the-silk-road-history-s-first-world-wide-web-shannon-harris-castelo With modern technology, a global exchange of goods and ideas can happen at the click of a button. WSC link: Where We’re Going, We’ll Still Need Them / Roads as hidden foundation.",
      "keyTerms": [
        "silk",
        "shannon",
        "castelo",
        "road",
        "trade",
        "harris",
        "ted",
        "ted-ed",
        "lesson",
        "global",
        "exchange",
        "history",
        "commerce",
        "thread",
        "steff",
        "lee",
        "globalization",
        "connecting"
      ],
      "transcriptAvailable": false,
      "sectionIds": [
        "call-of-duty-free"
      ],
      "sectionTitles": [
        "Call of Duty-Free"
      ],
      "entryTitles": [
        "When Goods Travel: The World of Trade Hubs"
      ],
      "bigIdeaLabels": [
        "Routes, Roads & Navigation",
        "Journeys",
        "Planning & Projects",
        "Progress",
        "Destinations",
        "Thresholds",
        "Tourism",
        "Roads as hidden foundation",
        "Historical list traditions",
        "Detours"
      ],
      "bigIdeaIds": [
        "routes-roads-and-navigation",
        "journeys",
        "planning-and-projects",
        "progress",
        "destinations",
        "thresholds",
        "tourism",
        "roads-as-hidden-foundation",
        "historical-list-traditions",
        "detours"
      ],
      "subjectLabels": [
        "Economics & Trade",
        "Geography / Human Geography"
      ],
      "subjectIds": [
        "economics-trade",
        "geography-human-geography"
      ],
      "connections": [
        {
          "kind": "entry",
          "sectionId": "call-of-duty-free",
          "sectionTitle": "Call of Duty-Free",
          "entryTitle": "When Goods Travel: The World of Trade Hubs",
          "why": "Manually placed under When Goods Travel: The World of Trade Hubs."
        }
      ],
      "sourceId": "playlist-052-vn3e37VWc0k",
      "canonicalSectionId": "call-of-duty-free",
      "assetId": null
    },
    {
      "id": "video.call-of-duty-free.003",
      "playlistIndex": 66,
      "title": "World’s first motel in San Luis Obispo marks 100 years but future remains uncertain",
      "channel": "KSBY News",
      "url": "https://www.youtube.com/watch?v=oQpO18Wxu0U",
      "duration": "2:29",
      "uploadDate": "2025-12-12T18:10:53-08:00",
      "viewCount": 679,
      "contentType": "educational or contextual video",
      "formatStyle": "mixed or unknown",
      "score": 6.8,
      "verdict": "Useful WSC support, especially with teacher framing.",
      "description": "World’s first motel in San Luis Obispo marks 100 years but future remains uncertain WSC link: Call of Duty-Free / Tourism types.",
      "keyTerms": [
        "news",
        "world",
        "first",
        "motel",
        "san",
        "luis",
        "obispo",
        "marks",
        "years",
        "future",
        "remains",
        "uncertain",
        "ksby",
        "local"
      ],
      "transcriptAvailable": false,
      "sectionIds": [
        "call-of-duty-free"
      ],
      "sectionTitles": [
        "Call of Duty-Free"
      ],
      "entryTitles": [
        "From Roadside Stops to Hotels"
      ],
      "bigIdeaLabels": [
        "Tourism",
        "Journeys",
        "Prediction",
        "Bright and Dark Future",
        "Routes, Roads & Navigation",
        "Tourism types",
        "AI as future symbol",
        "Retrofit logic",
        "What futurism does",
        "Retrofuturism"
      ],
      "bigIdeaIds": [
        "tourism",
        "journeys",
        "prediction",
        "bright-and-dark-future",
        "routes-roads-and-navigation",
        "tourism-types",
        "ai-as-future-symbol",
        "retrofit-logic",
        "what-futurism-does",
        "retrofuturism"
      ],
      "subjectLabels": [
        "History"
      ],
      "subjectIds": [
        "history"
      ],
      "connections": [
        {
          "kind": "entry",
          "sectionId": "call-of-duty-free",
          "sectionTitle": "Call of Duty-Free",
          "entryTitle": "From Roadside Stops to Hotels",
          "why": "Approved review placement under From Roadside Stops to Hotels."
        }
      ],
      "sourceId": "playlist-066-oQpO18Wxu0U",
      "canonicalSectionId": "call-of-duty-free",
      "assetId": null
    },
    {
      "id": "video.call-of-duty-free.004",
      "playlistIndex": 76,
      "title": "The Saturday Evening Post History Minute: What Happened to the American Motel?",
      "channel": "The Saturday Evening Post",
      "url": "https://www.youtube.com/watch?v=SbkCvXLgYYE",
      "duration": "4:35",
      "uploadDate": "2022-10-10T21:00:13-07:00",
      "viewCount": 3247,
      "contentType": "educational or contextual video",
      "formatStyle": "mixed or unknown",
      "score": 6.8,
      "verdict": "Useful WSC support, especially with teacher framing.",
      "description": "In the early 1950s, more than 40,000 motels dotted the American landscape. WSC link: Call of Duty-Free / Tourism types.",
      "keyTerms": [
        "saturday",
        "evening",
        "post",
        "american",
        "history",
        "minute",
        "happened",
        "motel",
        "early",
        "motels",
        "dotted",
        "landscape",
        "late",
        "century",
        "closed",
        "fallen",
        "disrepair",
        "many"
      ],
      "transcriptAvailable": false,
      "sectionIds": [
        "call-of-duty-free"
      ],
      "sectionTitles": [
        "Call of Duty-Free"
      ],
      "entryTitles": [
        "From Roadside Stops to Hotels"
      ],
      "bigIdeaLabels": [
        "Tourism",
        "Journeys",
        "Drafts & Prototypes",
        "Progress",
        "Endings",
        "Thresholds",
        "Prediction",
        "Bright and Dark Future",
        "Tourism types",
        "Manuscripts and crossed-out thinking"
      ],
      "bigIdeaIds": [
        "tourism",
        "journeys",
        "drafts-and-prototypes",
        "progress",
        "endings",
        "thresholds",
        "prediction",
        "bright-and-dark-future",
        "tourism-types",
        "manuscripts-and-crossed-out-thinking"
      ],
      "subjectLabels": [
        "History"
      ],
      "subjectIds": [
        "history"
      ],
      "connections": [
        {
          "kind": "entry",
          "sectionId": "call-of-duty-free",
          "sectionTitle": "Call of Duty-Free",
          "entryTitle": "From Roadside Stops to Hotels",
          "why": "Approved review placement under From Roadside Stops to Hotels."
        }
      ],
      "sourceId": "playlist-076-SbkCvXLgYYE",
      "canonicalSectionId": "call-of-duty-free",
      "assetId": null
    },
    {
      "id": "video.call-of-duty-free.005",
      "playlistIndex": 77,
      "title": "Countries crack down on rowdy tourists l GMA",
      "channel": "Good Morning America",
      "url": "https://www.youtube.com/watch?v=3iH6iqTiLQg",
      "duration": "3:19",
      "uploadDate": "2023-04-13T08:24:53-07:00",
      "viewCount": 1490054,
      "contentType": "educational or contextual video",
      "formatStyle": "mixed or unknown",
      "score": 7.4,
      "verdict": "Strong WSC candidate.",
      "description": "An Italian bill introduces new measures targeting cultural heritage vandals, with violations carrying a fine of up to 60,000 euros. WSC link: Call of Duty-Free / Tourism types.",
      "keyTerms": [
        "gma",
        "travel",
        "tourist",
        "tourists",
        "abc",
        "goodmorningamerica",
        "news",
        "rowdy",
        "good",
        "morning",
        "america",
        "vandals",
        "violations",
        "tiktok",
        "instagram",
        "facebook",
        "twitter",
        "tourism"
      ],
      "transcriptAvailable": false,
      "sectionIds": [
        "call-of-duty-free"
      ],
      "sectionTitles": [
        "Call of Duty-Free"
      ],
      "entryTitles": [
        "Traveling Differently: The Search for “Authentic” Tourism"
      ],
      "bigIdeaLabels": [
        "Tourism",
        "Journeys",
        "Home & Wandering",
        "Tourism types",
        "Exile vs chosen mobility",
        "Travel as status",
        "Duty-free culture",
        "Destinations"
      ],
      "bigIdeaIds": [
        "tourism",
        "journeys",
        "home-and-wandering",
        "tourism-types",
        "exile-vs-chosen-mobility",
        "travel-as-status",
        "duty-free-culture",
        "destinations"
      ],
      "subjectLabels": [
        "Sociology",
        "Media / Film"
      ],
      "subjectIds": [
        "sociology",
        "media-film"
      ],
      "connections": [
        {
          "kind": "entry",
          "sectionId": "call-of-duty-free",
          "sectionTitle": "Call of Duty-Free",
          "entryTitle": "Traveling Differently: The Search for “Authentic” Tourism",
          "why": "Approved review placement under Traveling Differently: The Search for “Authentic” Tourism."
        }
      ],
      "sourceId": "playlist-077-3iH6iqTiLQg",
      "canonicalSectionId": "call-of-duty-free",
      "assetId": null
    },
    {
      "id": "video.call-of-duty-free.006",
      "playlistIndex": 82,
      "title": "Exploring China's crazy Instagram culture",
      "channel": "aini",
      "url": "https://www.youtube.com/watch?v=dEB8V-dQ5aQ",
      "duration": "20:01",
      "uploadDate": "2026-01-30T01:00:55-08:00",
      "viewCount": 331546,
      "contentType": "educational or contextual video",
      "formatStyle": "mixed or unknown",
      "score": 7.4,
      "verdict": "Strong WSC candidate.",
      "description": "-Stay connected online wherever you are - Use the Promo Code AINIXN to get 20% OFF Nomad eSIMs. WSC link: Call of Duty-Free / Tourism types.",
      "keyTerms": [
        "china",
        "culture",
        "online",
        "chinese",
        "aini",
        "social",
        "media",
        "available",
        "amzn",
        "doi",
        "travel",
        "nomad",
        "people",
        "daka",
        "big",
        "study",
        "tourism",
        "html"
      ],
      "transcriptAvailable": false,
      "sectionIds": [
        "call-of-duty-free"
      ],
      "sectionTitles": [
        "Call of Duty-Free"
      ],
      "entryTitles": [
        "Traveling Differently: The Search for “Authentic” Tourism"
      ],
      "bigIdeaLabels": [
        "Tourism",
        "Journeys",
        "Tourism types",
        "Travel as status",
        "Overtourism and local cost",
        "From inns to hotels",
        "Destinations"
      ],
      "bigIdeaIds": [
        "tourism",
        "journeys",
        "tourism-types",
        "travel-as-status",
        "overtourism-and-local-cost",
        "from-inns-to-hotels",
        "destinations"
      ],
      "subjectLabels": [
        "Sociology",
        "Media / Film"
      ],
      "subjectIds": [
        "sociology",
        "media-film"
      ],
      "connections": [
        {
          "kind": "entry",
          "sectionId": "call-of-duty-free",
          "sectionTitle": "Call of Duty-Free",
          "entryTitle": "Traveling Differently: The Search for “Authentic” Tourism",
          "why": "Manually placed under Traveling Differently: The Search for “Authentic” Tourism."
        }
      ],
      "sourceId": "playlist-082-dEB8V-dQ5aQ",
      "canonicalSectionId": "call-of-duty-free",
      "assetId": null
    },
    {
      "id": "video.call-of-duty-free.007",
      "playlistIndex": 113,
      "title": "A V.I.P. Tour of London's Most Famous Hotel | Condé Nast Traveler",
      "channel": "Condé Nast Traveler",
      "url": "https://www.youtube.com/watch?v=LG3avHJ6ZrM",
      "duration": "5:48",
      "uploadDate": "2022-08-25T09:00:10-07:00",
      "viewCount": 16592,
      "contentType": "educational or contextual video",
      "formatStyle": "mixed or unknown",
      "score": 7.4,
      "verdict": "Strong WSC candidate.",
      "description": "Come inside London’s most famous hotel with Condé Nast Traveler as Managing Director Franck Arnold leads you on an exclusive tour of The Savoy. WSC link: Call of Duty-Free / Tourism types.",
      "keyTerms": [
        "hotel",
        "savoy",
        "nast",
        "traveler",
        "tour",
        "london",
        "famous",
        "cond",
        "conde",
        "director",
        "design",
        "inside",
        "travel",
        "hotels",
        "vip",
        "london's",
        "come",
        "managing"
      ],
      "transcriptAvailable": false,
      "sectionIds": [
        "call-of-duty-free"
      ],
      "sectionTitles": [
        "Call of Duty-Free"
      ],
      "entryTitles": [
        "From Roadside Stops to Hotels"
      ],
      "bigIdeaLabels": [
        "Tourism",
        "Journeys",
        "Home & Wandering",
        "Destinations",
        "Thresholds",
        "Tourism types",
        "From inns to hotels",
        "Return and homecoming",
        "False endings and near-endings",
        "Overtourism and local cost"
      ],
      "bigIdeaIds": [
        "tourism",
        "journeys",
        "home-and-wandering",
        "destinations",
        "thresholds",
        "tourism-types",
        "from-inns-to-hotels",
        "return-and-homecoming",
        "false-endings-and-near-endings",
        "overtourism-and-local-cost"
      ],
      "subjectLabels": [
        "History"
      ],
      "subjectIds": [
        "history"
      ],
      "connections": [
        {
          "kind": "entry",
          "sectionId": "call-of-duty-free",
          "sectionTitle": "Call of Duty-Free",
          "entryTitle": "From Roadside Stops to Hotels",
          "why": "Approved review placement under From Roadside Stops to Hotels."
        }
      ],
      "sourceId": "playlist-113-LG3avHJ6ZrM",
      "canonicalSectionId": "call-of-duty-free",
      "assetId": null
    },
    {
      "id": "video.call-of-duty-free.008",
      "playlistIndex": 114,
      "title": "Insider MALAY STREET FOOD TOUR at Night Market Jalan TAR in Kuala, Lumpur!",
      "channel": "Best Ever Food Review Show",
      "url": "https://www.youtube.com/watch?v=cYc8JfglL-A",
      "duration": "12:05",
      "uploadDate": "2017-10-23T10:27:38-07:00",
      "viewCount": 1207972,
      "contentType": "educational or contextual video",
      "formatStyle": "mixed or unknown",
      "score": 7.4,
      "verdict": "Strong WSC candidate.",
      "description": "How To Cook Lunch For 800 People in Guangzhou, China → https://www.youtube.com/watch?v=7rPV2AB-mTQ Join the notification squad! WSC link: Call of Duty-Free / Tourism types.",
      "keyTerms": [
        "food",
        "street",
        "kuala",
        "lumpur",
        "jalan",
        "show",
        "otak",
        "malay",
        "best",
        "ever",
        "review",
        "people",
        "malaysian",
        "instagram",
        "facebook",
        "besteverfoodreviewshow",
        "support",
        "patreon"
      ],
      "transcriptAvailable": false,
      "sectionIds": [
        "call-of-duty-free"
      ],
      "sectionTitles": [
        "Call of Duty-Free"
      ],
      "entryTitles": [
        "Traveling Differently: The Search for “Authentic” Tourism"
      ],
      "bigIdeaLabels": [
        "Tourism",
        "Journeys",
        "Home & Wandering",
        "Adulthood",
        "Transition",
        "Destinations",
        "Thresholds",
        "Tourism types",
        "Homesickness",
        "Adaptation and migration"
      ],
      "bigIdeaIds": [
        "tourism",
        "journeys",
        "home-and-wandering",
        "adulthood",
        "transition",
        "destinations",
        "thresholds",
        "tourism-types",
        "homesickness",
        "adaptation-and-migration"
      ],
      "subjectLabels": [
        "Sociology",
        "Media / Film"
      ],
      "subjectIds": [
        "sociology",
        "media-film"
      ],
      "connections": [
        {
          "kind": "entry",
          "sectionId": "call-of-duty-free",
          "sectionTitle": "Call of Duty-Free",
          "entryTitle": "Traveling Differently: The Search for “Authentic” Tourism",
          "why": "Approved review placement under Traveling Differently: The Search for “Authentic” Tourism."
        }
      ],
      "sourceId": "playlist-114-cYc8JfglL-A",
      "canonicalSectionId": "call-of-duty-free",
      "assetId": null
    },
    {
      "id": "video.call-of-duty-free.009",
      "playlistIndex": 120,
      "title": "Is Rome being ruined by crowds?",
      "channel": "Mary McGillivray",
      "url": "https://www.youtube.com/watch?v=V2AjTZG_D8g",
      "duration": "4:39",
      "uploadDate": "2023-09-01T21:53:55-07:00",
      "viewCount": 4696,
      "contentType": "educational or contextual video",
      "formatStyle": "mixed or unknown",
      "score": 6.2,
      "verdict": "Metadata-only candidate; review manually before relying on it.",
      "description": "Turns out American tourist jokes are as old as time... WSC link: The Lovely and the Liminal / Liminal spaces in architecture.",
      "keyTerms": [
        "part",
        "mary",
        "mcgillivray",
        "playlist",
        "youtu",
        "patreon",
        "theiconoclass",
        "tiktok",
        "instagram",
        "rome",
        "ruined",
        "crowds",
        "turns",
        "american",
        "tourist",
        "jokes",
        "old",
        "time"
      ],
      "transcriptAvailable": false,
      "sectionIds": [
        "call-of-duty-free"
      ],
      "sectionTitles": [
        "Call of Duty-Free"
      ],
      "entryTitles": [
        "Traveling Differently: The Search for “Authentic” Tourism"
      ],
      "bigIdeaLabels": [
        "Liminality",
        "Waiting",
        "Drafts & Prototypes",
        "Prediction",
        "Liminal spaces in architecture",
        "What a prototype is",
        "Minimum viable product",
        "Prototype ethics",
        "Tourism"
      ],
      "bigIdeaIds": [
        "liminality",
        "waiting",
        "drafts-and-prototypes",
        "prediction",
        "liminal-spaces-in-architecture",
        "what-a-prototype-is",
        "minimum-viable-product",
        "prototype-ethics",
        "tourism"
      ],
      "subjectLabels": [
        "Sociology",
        "Media / Film"
      ],
      "subjectIds": [
        "sociology",
        "media-film"
      ],
      "connections": [
        {
          "kind": "entry",
          "sectionId": "call-of-duty-free",
          "sectionTitle": "Call of Duty-Free",
          "entryTitle": "Traveling Differently: The Search for “Authentic” Tourism",
          "why": "Approved review placement under Traveling Differently: The Search for “Authentic” Tourism."
        }
      ],
      "sourceId": "playlist-120-V2AjTZG_D8g",
      "canonicalSectionId": "call-of-duty-free",
      "assetId": null
    },
    {
      "id": "video.call-of-duty-free.010",
      "playlistIndex": 121,
      "title": "Subject knowledge animation: What is Ecotourism?",
      "channel": "Royal Geographical Society",
      "url": "https://www.youtube.com/watch?v=1i4ioqIaXrE",
      "duration": "2:24",
      "uploadDate": "2017-03-14T10:24:43-07:00",
      "viewCount": 306090,
      "contentType": "pedagogical explainer",
      "formatStyle": "mixed or unknown",
      "score": 6.8,
      "verdict": "Useful WSC support, especially with teacher framing.",
      "description": "What are the three key principles of Ecotourism? WSC link: Call of Duty-Free / Tourism types.",
      "keyTerms": [
        "ecotourism",
        "subject",
        "knowledge",
        "animation",
        "environment",
        "royal",
        "geographical",
        "society",
        "three",
        "key",
        "principles",
        "explores",
        "tourism",
        "protects",
        "supports",
        "local",
        "people",
        "geography"
      ],
      "transcriptAvailable": false,
      "sectionIds": [
        "call-of-duty-free"
      ],
      "sectionTitles": [
        "Call of Duty-Free"
      ],
      "entryTitles": [
        "Traveling Differently: The Search for “Authentic” Tourism"
      ],
      "bigIdeaLabels": [
        "Tourism",
        "Journeys",
        "Destinations",
        "Thresholds",
        "Tourism types",
        "Overtourism and local cost",
        "From inns to hotels",
        "Destination vs journey"
      ],
      "bigIdeaIds": [
        "tourism",
        "journeys",
        "destinations",
        "thresholds",
        "tourism-types",
        "overtourism-and-local-cost",
        "from-inns-to-hotels",
        "destination-vs-journey"
      ],
      "subjectLabels": [
        "Sociology",
        "Media / Film"
      ],
      "subjectIds": [
        "sociology",
        "media-film"
      ],
      "connections": [
        {
          "kind": "entry",
          "sectionId": "call-of-duty-free",
          "sectionTitle": "Call of Duty-Free",
          "entryTitle": "Traveling Differently: The Search for “Authentic” Tourism",
          "why": "Approved review placement under Traveling Differently: The Search for “Authentic” Tourism."
        }
      ],
      "sourceId": "playlist-121-1i4ioqIaXrE",
      "canonicalSectionId": "call-of-duty-free",
      "assetId": null
    },
    {
      "id": "video.call-of-duty-free.011",
      "playlistIndex": 122,
      "title": "How ‘trashy’ tourism threatens world-famous destinations",
      "channel": "Global News",
      "url": "https://www.youtube.com/watch?v=9aW_Dlq0lnk",
      "duration": "2:51",
      "uploadDate": "2019-06-28T14:56:43-07:00",
      "viewCount": 60793,
      "contentType": "pedagogical explainer",
      "formatStyle": "documentary/news footage with voiceover",
      "score": 7.6,
      "verdict": "Strong WSC candidate.",
      "description": "Contextual video about How ‘trashy’ tourism threatens world-famous destinations. WSC link: Call of Duty-Free / Tourism types.",
      "keyTerms": [
        "news",
        "global",
        "tourists",
        "bit",
        "tourism",
        "destinations",
        "garbage",
        "trash",
        "globalnews",
        "follow",
        "trashy",
        "threatens",
        "world-famous",
        "info",
        "please",
        "tourism-pollution-world-famous-destinations",
        "subscribe",
        "fcxdc"
      ],
      "transcriptAvailable": false,
      "sectionIds": [
        "call-of-duty-free"
      ],
      "sectionTitles": [
        "Call of Duty-Free"
      ],
      "entryTitles": [
        "Traveling Differently: The Search for “Authentic” Tourism"
      ],
      "bigIdeaLabels": [
        "Tourism",
        "Journeys",
        "Home & Wandering",
        "Tourism types",
        "Travel as status",
        "Airport life as limbo",
        "Exile vs chosen mobility",
        "Destinations"
      ],
      "bigIdeaIds": [
        "tourism",
        "journeys",
        "home-and-wandering",
        "tourism-types",
        "travel-as-status",
        "airport-life-as-limbo",
        "exile-vs-chosen-mobility",
        "destinations"
      ],
      "subjectLabels": [
        "Sociology",
        "Media / Film"
      ],
      "subjectIds": [
        "sociology",
        "media-film"
      ],
      "connections": [
        {
          "kind": "entry",
          "sectionId": "call-of-duty-free",
          "sectionTitle": "Call of Duty-Free",
          "entryTitle": "Traveling Differently: The Search for “Authentic” Tourism",
          "why": "Approved review placement under Traveling Differently: The Search for “Authentic” Tourism."
        }
      ],
      "sourceId": "playlist-122-9aW_Dlq0lnk",
      "canonicalSectionId": "call-of-duty-free",
      "assetId": null
    }
  ]
}
